DAO/__init__.py
DAO/base.py
DAO/database.py
DAO/db_initializer.py
DAO/master_tables/__init__.py
DAO/master_tables/accounting_charge_type.py
DAO/master_tables/denomination.py
DAO/master_tables/platform.py
DAO/master_tables/receipt_amount_type.py
DAO/master_tables/transaction_type.py
DAO/master_tables/transfer_status.py
DAO/master_tables/transfer_type.py
DAO_layer-0.0.2.dist-info/METADATA
DAO_layer-0.0.2.dist-info/WHEEL
DAO_layer-0.0.2.dist-info/top_level.txt
DAO_layer-0.0.2.dist-info/RECORD
