Metadata-Version: 2.1
Name: DAO_layer
Version: 0.0.2
Summary: DAO Layer packaging
Author: Kogta Fin
Author-email: <vijayl.ext@kogta.in>
Keywords: python,first package
Classifier: Development Status :: 1 - Planning
Classifier: Intended Audience :: Education
Classifier: Programming Language :: Python :: 3
Classifier: Operating System :: Unix
Classifier: Operating System :: MacOS
